mosaik_pypower/__init__.py
mosaik_pypower/model.py
mosaik_pypower/mosaik.py
mosaik_pypower/resource_db.py
mosaik.PyPower_SemVer-0.7.3rc20211214010523.dist-info/AUTHORS.txt
mosaik.PyPower_SemVer-0.7.3rc20211214010523.dist-info/LICENSE.txt
mosaik.PyPower_SemVer-0.7.3rc20211214010523.dist-info/METADATA
mosaik.PyPower_SemVer-0.7.3rc20211214010523.dist-info/WHEEL
mosaik.PyPower_SemVer-0.7.3rc20211214010523.dist-info/entry_points.txt
mosaik.PyPower_SemVer-0.7.3rc20211214010523.dist-info/top_level.txt
mosaik.PyPower_SemVer-0.7.3rc20211214010523.dist-info/RECORD
