Metadata-Version: 2.1
Name: mosaik.PyPower-SemVer
Version: 0.7.3rc20211214010523
Summary: An adapter to use PYPOWER with mosaik.
Home-page: https://bitbucket.org/mosaik/mosaik-pypower
Author: Stefan Scherfke
Author-email: stefan.scherfke@offis.de
Maintainer: Bengt Lüers
Maintainer-email: bengt.lueers@gmail.com
License: UNKNOWN
Platform: UNKNOWN
Classifier: Development Status :: 4 - Beta
Classifier: Environment :: Console
Classifier: Intended Audience :: Science/Research
Classifier: License :: OSI Approved :: GNU Lesser General Public License v2 (LGPLv2)
Classifier: Natural Language :: English
Classifier: Operating System :: OS Independent
Classifier: Programming Language :: Python
Classifier: Programming Language :: Python :: 3
Classifier: Programming Language :: Python :: 3.7
Classifier: Programming Language :: Python :: 3.8
Classifier: Programming Language :: Python :: 3.9
Classifier: Topic :: Scientific/Engineering
Requires-Dist: PYPOWER (>=4.1)
Requires-Dist: mosaik.API-SemVer (>=2.4.2rc20190716091443)
Requires-Dist: mosaik.Core-SemVer (>=2.5.2rc20190715231038)
Requires-Dist: numpy (>=1.6)
Requires-Dist: scipy (>=0.9)
Requires-Dist: xlrd (<1.2.0,>=0.9.2)
